brad/__init__.py
brad/exceptions.py
brad/resample.py
brad/results.py
brad/samplers.py
brad-0.2.0a0.dist-info/LICENSE
brad-0.2.0a0.dist-info/METADATA
brad-0.2.0a0.dist-info/WHEEL
brad-0.2.0a0.dist-info/top_level.txt
brad-0.2.0a0.dist-info/RECORD
