Metadata-Version: 2.1
Name: brad
Version: 0.2.0a0
Summary: Brad is a Python package for Bootstrap, permutation tests and other resampling functions.
Home-page: https://github.com/tcbegley/brad
Author: tcbegley
Author-email: tomcbegley@gmail.com
License: MIT
Platform: UNKNOWN
Classifier: Development Status :: 3 - Alpha
Classifier: License :: OSI Approved :: MIT License
Classifier: Programming Language :: Python :: 3.7
Classifier: Programming Language :: Python :: 3.8
Classifier: Programming Language :: Python :: 3.9
Requires-Dist: numpy (<2.0.0,>=1.18.0)
Requires-Dist: scikit-learn (>0.24.0)
Requires-Dist: scipy (<2.0.0,>=1.4.1)
Requires-Dist: importlib-metadata (<4.0.0,>=3.4.0) ; python_version == "3.7"
